woodblock/__init__.py
woodblock/__main__.py
woodblock/datagen.py
woodblock/errors.py
woodblock/file.py
woodblock/fragments.py
woodblock/image.py
woodblock/random.py
woodblock/scenario.py
woodblock/utils.py
woodblock-0.1.7.dist-info/LICENSE
woodblock-0.1.7.dist-info/METADATA
woodblock-0.1.7.dist-info/WHEEL
woodblock-0.1.7.dist-info/entry_points.txt
woodblock-0.1.7.dist-info/top_level.txt
woodblock-0.1.7.dist-info/RECORD
