Metadata-Version: 2.1
Name: woodblock
Version: 0.1.7
Summary: A framework to generate file carving test data
Home-page: https://github.com/fkie-cad/woodblock/
Author: Fraunhofer FKIE
Author-email: martin.lambertz@fkie.fraunhofer.de
License: MIT
Project-URL: Documentation, https://fkie-cad.github.io/woodblock/
Project-URL: Source, https://github.com/fkie-cad/woodblock/
Project-URL: Tracker, https://github.com/fkie-cad/woodblock/issues
Platform: UNKNOWN
Classifier: Programming Language :: Python :: 3
Classifier: License :: OSI Approved :: MIT License
Requires-Python: >3.6
Requires-Dist: click
Requires-Dist: multimethod
Requires-Dist: numpy
